wbauth/__init__.py
wbauth/authenticator.py
wbauth/constants.py
wbauth/utils.py
wbauth/telegram/handlers.py
wbauth-0.1.0.dist-info/METADATA
wbauth-0.1.0.dist-info/WHEEL
wbauth-0.1.0.dist-info/top_level.txt
wbauth-0.1.0.dist-info/RECORD
